lbpqc/__init__.py
lbpqc/type_aliases.py
lbpqc/cryptosystems/__init__.py
lbpqc/primitives/__init__.py
lbpqc/primitives/matrix.py
lbpqc/primitives/rng.py
lbpqc/primitives/integer/__init__.py
lbpqc/primitives/integer/integer_ring.py
lbpqc/primitives/integer/prime.py
lbpqc/primitives/lattice/__init__.py
lbpqc/primitives/lattice/embeddings.py
lbpqc/primitives/lattice/fullrank.py
lbpqc/primitives/lattice/reductions.py
lbpqc/primitives/polynomial/__init__.py
lbpqc/primitives/polynomial/modpoly.py
lbpqc/primitives/polynomial/poly.py
lbpqc/primitives/polynomial/polyqring.py
lbpqc-0.0.1.dist-info/LICENSE
lbpqc-0.0.1.dist-info/METADATA
lbpqc-0.0.1.dist-info/WHEEL
lbpqc-0.0.1.dist-info/top_level.txt
lbpqc-0.0.1.dist-info/RECORD
