Metadata-Version: 2.1
Name: lbpqc
Version: 0.0.1
Summary: A library of primitives for teaching lattice-based post-quantum cryptography
Author-email: Mikołaj Leonhardt <mikolaj.leonhardt@gmail.com>
License: This is free and unencumbered software released into the public domain.
Project-URL: Repository, https://github.com/mikolajlh/lbpqc.git
Project-URL: Documentation, https://mikolajlh.github.io/lbpqc/
Keywords: cryptography,lattice,NTRU,LWE,LWR,GGH
Classifier: Development Status :: 2 - Pre-Alpha
Classifier: Programming Language :: Python
Classifier: Programming Language :: Python :: 3 :: Only
Classifier: License :: OSI Approved :: The Unlicense (Unlicense)
Classifier: Operating System :: OS Independent
Classifier: Intended Audience :: Education
Classifier: Topic :: Security :: Cryptography
Requires-Python: >=3.8
License-File: LICENSE
Requires-Dist: numpy
